LICENSE
piligraphs/__init__.py
piligraphs/funcgraph.py
piligraphs/graph.py
piligraphs/linechart.py
piligraphs/node.py
piligraphs/piechart.py
piligraphs/radarchart.py
piligraphs/utils.py
pyproject.toml
piligraphs-0.0.7.dist-info/LICENSE
piligraphs-0.0.7.dist-info/METADATA
piligraphs-0.0.7.dist-info/WHEEL
piligraphs-0.0.7.dist-info/RECORD
