Metadata-Version: 2.1
Name: piligraphs
Version: 0.0.7
Summary: A Pillow extension for drawing graphs and charts.
Home-page: https://github.com/eeemoon/piligraphs
License: MIT
Author: EeeMoon
Requires-Python: >=3.10,<4.0
Classifier: License :: OSI Approved :: MIT License
Classifier: Programming Language :: Python :: 3
Classifier: Programming Language :: Python :: 3.10
Classifier: Programming Language :: Python :: 3.11
Classifier: Programming Language :: Python :: 3.12
Requires-Dist: Pillow (>=10.4.0,<11.0.0)
Requires-Dist: numpy (>=2.0.0,<3.0.0)
Requires-Dist: pinkie (>=0.0.2,<0.0.3)
Requires-Dist: scipy (>=1.14.0,<2.0.0)
